{
  "title": "Trust Badges",
  "badges": [
    {
      "id": "1",
      "imageUrl": "https://https://c.animaapp.com/mgrzhz36mRAJyZ/assets/power-elite.pngc.animaapp.com/mgrzhz36mRAJyZ/assets/badge-1.svg",
      "altText": "Premium Quality",
      "text": "dwdwdwd",
      "icon": "dwdwd"
    },
    {
      "id": "2",
      "imageUrl": "httphttps://c.animaapp.com/mgrzhz36mRAJyZ/assets/power-elite.pngs://c.animaapp.com/mgrzhz36mRAJyZ/assets/badge-2.svg",
      "altText": "Trusted Brand",
      "text": "wdwdw"
    }
  ],
  "description": "dwdwddwd"
}