{
  "backgroundImage": "https://bella-beauty.cmsmasters.studio/wp-content/uploads/2024/03/landing-1.webp",
  "overlayOpacity": 0.1,
  "overlayColor": "#000000",
  "title": "test 2 dwdwdwddqwdqwdqdqwd dwqdq",
  "subtitle": "wefwfwefwf efwef fwefewf dwdqwd f dqwd efefwefwe dwdwd ",
  "buttonText": "Purchase   feffefefdqwd dwq dwdqdqdqwedqwdqwdqw wefwef",
  "buttonLink": "https://1.envato.market/cmsmasters-bella-beauty dwdqwd",
  "viewDemosText": "View Demos",
  "viewDemosLink": "#demos",
  "additionalText": "Take your website to the next level.",
  "secondaryText": " ffwefwefwe"
}