{
  "backgroundImage": "https://bellawdwdbeauty.cmsmasters.studio/wp-content/uploads/2024/03/landing-1.webp",
  "overlayOpacity": 0.1,
  "overlayColor": "#000000",
  "title": "prod test 1.1",
  "subtitle": "wefwfwefwf efwef fwefewf dwdqwd f dqwd efefwefwe dwdwd ",
  "buttonText": "rfrfrf",
  "buttonLink": "https://1.envato.market/cmsmasters-bella-beau",
  "viewDemosText": "View Demos",
  "viewDemosLink": "#demos",
  "additionalText": "Take your website to the next level.",
  "secondaryText": " ffwefwefwefrfr",
  "secondaryButtonText": "rfrfrf"
}